eclectic/__init__.py
eclectic/api.py
eclectic/conftest.py
eclectic/middleware.py
eclectic/response.py
eclectic/test_eclectic.py
eclectic-0.0.2.dist-info/LICENSE.md
eclectic-0.0.2.dist-info/METADATA
eclectic-0.0.2.dist-info/WHEEL
eclectic-0.0.2.dist-info/top_level.txt
eclectic-0.0.2.dist-info/RECORD
