Metadata-Version: 2.1
Name: eclectic
Version: 0.0.2
Summary: Eclectic Python Web Framework built by Eclecticlly.
Author: Massimiliano Bertinetti
Author-email: max@eclecticlly.com
License: MIT
Platform: UNKNOWN
Classifier: Programming Language :: Python :: 3.9
Requires-Python: >=3.9.0
License-File: LICENSE.md
Requires-Dist: Jinja2 (==3.0.3)
Requires-Dist: parse (==1.19.0)
Requires-Dist: requests (==2.27.1)
Requires-Dist: requests-wsgi-adapter (==0.4.1)
Requires-Dist: WebOb (==1.8.7)
Requires-Dist: whitenoise (==6.0.0)
